{
  "currency": "EUR",
  "categories": {
    "liquids": {
      "title": "💧 Рідини",
      "brands": {
        "ELFLIQ": {
          "price": 19,
          "nicotine": "5%",
          "items": [
            "🍎 APPLE PEACH",
            "🍇 BLACKCURRANT ANISEED",
            "🫐 BLUE RAZZ LEMONADE",
            "🫐 BLUEBERRY",
            "🍒 CHERRY",
            "❄️ PEACH ICE",
            "🍊 PINK GRAPEFRUIT",
            "🌿 SPEARMINT",
            "🍓 STRAWBERRY ICE",
            "🍉 WATERMELON CHERRY"
          ]
        },
        "CHASER": {
          "price": 20,
          "volume": "30 ML",
          "nicotine": "50 MG",
          "items": [
            "🥝 KIWI PASSION FRUIT GUAVA",
            "🍑 PEACH TEA",
            "🍏 SOUR APPLE",
            "🍓 STRAWBERRY CREAM",
            "🍉 WATERMELON RASPBERRY"
          ]
        },
        "HQD": {
          "price": 18,
          "type": "PREMIUM SALT",
          "nicotine": "5%",
          "items": [
            "🍒 CHERRY ICE",
            "🍋 LEMON LIME",
            "🫐 BLUEBERRY LEMONADE",
            "🍓 STRAWBERRY ICE"
          ]
        }
      }
    }
  }
}
